setup.py
caracteres/__init__.py
caracteres/carater_finder.py
ghhu/__init__.py
ghhu/github.py
ghhu.egg-info/PKG-INFO
ghhu.egg-info/SOURCES.txt
ghhu.egg-info/dependency_links.txt
ghhu.egg-info/not-zip-safe
ghhu.egg-info/requires.txt
ghhu.egg-info/top_level.txt
intro/__init__.py
intro/arquivos.py
intro/cc.py
intro/dicionario.py
intro/list_comp.py
intro/listas.py
intro/maximo.py
intro/produto_cartesiano.py
intro/tuplas_e_conjuntos.py