Metadata-Version: 1.1
Name: ghhu
Version: 0.1
Summary: Projeto de Exemplo para curso no Hotel Urbano
Home-page: https://github.com/renzon/hotel-urbano
Author: Renzo Nuccitelli
Author-email: renzon@gmail.com
License: BSD
Platform: UNKNOWN
Classifier: Development Status :: 4 - Beta
Classifier: Environment :: Web Environment
Classifier: Intended Audience :: Developers
Classifier: License :: OSI Approved :: BSD License
Classifier: Operating System :: OS Independent
Classifier: Programming Language :: Python
Classifier: Framework :: Paste
